Phashcat/__init__.py
Phashcat/hashcat/__init__.py
Phashcat/hashcat/hashcat.exe
Phashcat/hashcat/hashcat.hcstat2
Phashcat/hashcat/hashcat_builder.py
Phashcat/hashcat/hashcat_flags.py
phashcat-0.1.1.dist-info/licenses/LICENSE
phashcat-0.1.1.dist-info/METADATA
phashcat-0.1.1.dist-info/WHEEL
phashcat-0.1.1.dist-info/top_level.txt
phashcat-0.1.1.dist-info/RECORD
