Metadata-Version: 2.4
Name: Phashcat
Version: 0.1.1
Summary: Pythonic monoid-style builder around hashcat CLI with bundled binary.
Author: Avi Twil
License: MIT
Project-URL: Homepage, https://github.com/avitwil/Phashcat
Project-URL: Issues, https://github.com/avitwil/Phashcat/issues
Keywords: hashcat,cli,wrapper,security,pentest,builder,monoid
Classifier: Development Status :: 3 - Alpha
Classifier: Intended Audience :: Developers
Classifier: Intended Audience :: Information Technology
Classifier: Intended Audience :: Science/Research
Classifier: Topic :: Security
Classifier: Topic :: Utilities
Classifier: License :: OSI Approved :: MIT License
Classifier: Programming Language :: Python :: 3
Classifier: Programming Language :: Python :: 3.9
Classifier: Programming Language :: Python :: 3.10
Classifier: Programming Language :: Python :: 3.11
Classifier: Programming Language :: Python :: 3.12
Classifier: Programming Language :: Python :: 3.13
Requires-Python: >=3.9
License-File: LICENSE
Dynamic: license-file
